scapula_predict/__init__.py
scapula_predict-0.0.10.dist-info/METADATA
scapula_predict-0.0.10.dist-info/WHEEL
scapula_predict-0.0.10.dist-info/licenses/LICENSE
scapula_predict-0.0.10.dist-info/RECORD
