Metadata-Version: 2.1
Name: scapula_predict
Version: 0.0.10
Summary: Scapula Predict
Author-email: wxy <837038599@qq.com>
License: Copyright (c) 2018 The Python Packaging Authority
License-File: LICENSE
Classifier: License :: OSI Approved :: MIT License
Classifier: Operating System :: Microsoft :: Windows :: Windows 11
Classifier: Programming Language :: Python :: 3
Requires-Python: >=3.7
